dash_jbrowse/CircularGenomeView.py
dash_jbrowse/LinearGenomeView.py
dash_jbrowse/__init__.py
dash_jbrowse/_imports_.py
dash_jbrowse/dash_jbrowse.min.js
dash_jbrowse/metadata.json
dash_jbrowse/package-info.json
dash_jbrowse-1.4.2.dist-info/LICENSE
dash_jbrowse-1.4.2.dist-info/METADATA
dash_jbrowse-1.4.2.dist-info/WHEEL
dash_jbrowse-1.4.2.dist-info/top_level.txt
dash_jbrowse-1.4.2.dist-info/RECORD
