Metadata-Version: 2.1
Name: dash-jbrowse
Version: 1.4.2
Summary: Dash components for JBrowse 2
Home-page: https://github.com/GMOD/dash_jbrowse
Author: Elliot Hershberg <eahershberg@gmail.com>
Author-email: eahershberg@gmail.com
Maintainer: Teresa De Jesus Martinez
Maintainer-email: tere486martinez@gmail.com
License: Apache-2.0
Project-URL: Tracker, https://github.com/GMOD/dash_jbrowse/issues
Project-URL: Source, https://github.com/GMOD/dash_jbrowse/
Classifier: Framework :: Dash
Classifier: Programming Language :: Python :: 3
Classifier: Topic :: Scientific/Engineering :: Bio-Informatics
Classifier: Topic :: Scientific/Engineering :: Visualization
Classifier: License :: OSI Approved :: Apache Software License
Classifier: Intended Audience :: Science/Research
License-File: LICENSE
Requires-Dist: dash >=1.15.0
